{
  "courses": [
    {
      "id": 1,
      "title": "Tes Lagi",
      "description": "Ini adalah deskripsi",
      "image_thumbnail": "",
      "createdAt": "2022-11-01T11:40:15.000Z",
      "updatedAt": "2022-11-01T11:40:15.000Z",
      "id_division": 3,
      "id_user": 16
    },
    {
      "id": 2,
      "title": "Lorem ipsum",
      "description": "Lorem ipsum dolor sit amet",
      "image_thumbnail": "",
      "createdAt": "2022-11-01T11:40:15.000Z",
      "updatedAt": "2022-11-01T11:40:15.000Z",
      "id_division": 1,
      "id_user": 15
    }
  ]
}
